justoneapi/__init__.py
justoneapi/client.py
justoneapi/config.py
justoneapi/log.py
justoneapi/apis/__init__.py
justoneapi/apis/bilibili.py
justoneapi/apis/douyin.py
justoneapi/apis/jd.py
justoneapi/apis/kuaishou.py
justoneapi/apis/request_util.py
justoneapi/apis/search.py
justoneapi/apis/taobao.py
justoneapi/apis/tiktok.py
justoneapi/apis/toutiao.py
justoneapi/apis/user.py
justoneapi/apis/weibo.py
justoneapi/apis/xiaohongshu.py
justoneapi-1.16.0.dist-info/licenses/LICENSE
justoneapi-1.16.0.dist-info/METADATA
justoneapi-1.16.0.dist-info/WHEEL
justoneapi-1.16.0.dist-info/top_level.txt
justoneapi-1.16.0.dist-info/RECORD
