Metadata-Version: 2.4
Name: justoneapi
Version: 1.16.0
Summary: Official Python SDK for Just One API
Author-email: Just One API <support@justoneapi.com>
License-File: LICENSE
Requires-Dist: requests
Dynamic: license-file
